django_esutils
