Metadata-Version: 1.1
Name: django-esutils
Version: 0.2.3
Summary: Django Esutils.
Home-page: https://github.com/novapost/django-esutils
Author: Novapost
Author-email: florent.pigout@novapost.fr
License: MIT License
Platform: UNKNOWN
Classifier: Development Status :: 3 - Alpha
Classifier: Programming Language :: Python
Classifier: Framework :: Django
Classifier: License :: OSI Approved :: MIT License
